rectorch/__init__.py
rectorch/configuration.py
rectorch/data.py
rectorch/evaluation.py
rectorch/metrics.py
rectorch/models.py
rectorch/nets.py
rectorch/samplers.py
rectorch/tests/test_configuration.py
rectorch/tests/test_data.py
rectorch/tests/test_evaluation.py
rectorch/tests/test_metrics.py
rectorch/tests/test_models.py
rectorch/tests/test_nets.py
rectorch/tests/test_samplers.py
rectorch-0.0.9b0.dist-info/LICENSE
rectorch-0.0.9b0.dist-info/METADATA
rectorch-0.0.9b0.dist-info/WHEEL
rectorch-0.0.9b0.dist-info/top_level.txt
rectorch-0.0.9b0.dist-info/RECORD
