Metadata-Version: 2.1
Name: rectorch
Version: 0.0.9b0
Summary: rectorch: state-of-the-art recsys approaches implemented in pytorch.
Home-page: https://github.com/makgyver/rectorch
Author: Mirko Polato
Author-email: mak1788@gmail.com
License: MIT
Download-URL: https://github.com/makgyver/rectorch
Keywords: recommender-system,pytorch,machine-learning,algorithm,variational-autoencoder,gan
Platform: UNKNOWN
Classifier: Development Status :: 4 - Beta
Classifier: Programming Language :: Python :: 3.7
Classifier: Topic :: Scientific/Engineering :: Artificial Intelligence
Classifier: License :: OSI Approved :: MIT License
Requires-Python: >=3.6
Requires-Dist: numpy
Requires-Dist: scipy
Requires-Dist: torch
Requires-Dist: Bottleneck
Requires-Dist: munch
